{
  "resourceType": "Questionnaire",
  "title": "Common Criteria Related to Risk Assessment Evidence Collection Form",
  "status": "draft",
  "item": [
    {
      "item": [
        {
          "item": [
            {
              "type": "string",
              "linkId": "840840352670",
              "text": "Please provide the URL to Risk Assessment/Management Policy details.",
              "enableWhen": [
                {
                  "question": "527806457131",
                  "operator": "=",
                  "answerCoding": {
                    "display": "Yes"
                  }
                }
              ],
              "item": [
                {
                  "linkId": "884795523698",
                  "type": "display",
                  "text": "Provide evidence as a URL along with details of Dropbox, Box, Google Drive, Portal, or other storage platforms.",
                  "extension": [
                    {
                      "url": "http://hl7.org/fhir/StructureDefinition/questionnaire-itemControl",
                      "valueCodeableConcept": {
                        "coding": [
                          {
                            "system": "http://hl7.org/fhir/questionnaire-item-control",
                            "code": "help",
                            "display": "Help-Button"
                          }
                        ],
                        "text": "Help-Button"
                      }
                    }
                  ]
                }
              ]
            },
            {
              "type": "display",
              "linkId": "254358462696",
              "_text": {
                "extension": [
                  {
                    "url": "http://hl7.org/fhir/StructureDefinition/rendering-xhtml",
                    "valueString": "<p>If you don't have Risk Assessment/Management Policy details as evidence, you can refer the our sample version <span style=\"color:blue; text-decoration:none; cursor:pointer;\"  onclick=\"window.open('https://suite.opsfolio.com/policies/common/information-technology-quality-infrastructure/risk-management-policy', '_blank')\">here</span></p>"
                  }
                ]
              },
              "enableWhen": [
                {
                  "question": "527806457131",
                  "operator": "=",
                  "answerCoding": {
                    "display": "No"
                  }
                }
              ]
            },
            {
              "linkId": "442642457190",
              "type": "display",
              "text": "As evidence, you can provide Risk Assessment/Management Policy details.",
              "extension": [
                {
                  "url": "http://hl7.org/fhir/StructureDefinition/questionnaire-itemControl",
                  "valueCodeableConcept": {
                    "coding": [
                      {
                        "system": "http://hl7.org/fhir/questionnaire-item-control",
                        "code": "help",
                        "display": "Help-Button"
                      }
                    ],
                    "text": "Help-Button"
                  }
                }
              ]
            }
          ],
          "type": "choice",
          "extension": [
            {
              "url": "http://hl7.org/fhir/StructureDefinition/questionnaire-itemControl",
              "valueCodeableConcept": {
                "coding": [
                  {
                    "system": "http://hl7.org/fhir/questionnaire-item-control",
                    "code": "radio-button",
                    "display": "Radio Button"
                  }
                ]
              }
            }
          ],
          "linkId": "527806457131",
          "code": [
            {
              "code": "FII-SCF-RSK-0001"
            }
          ],
          "text": "Please describe your annual risk assessment process in regards to your service under review. (i.e., Risk assessments should identify, quantify, and prioritize risks against criteria for risk acceptance and objectives relevant to the organization. The results should guide and determine the appropriate management action and priorities for managing information security risks and for implementing controls selected to protect against these risks.)",
          "answerOption": [
            {
              "valueCoding": {
                "display": "Yes"
              }
            },
            {
              "valueCoding": {
                "display": "No"
              }
            }
          ]
        },
        {
          "item": [
            {
              "type": "string",
              "linkId": "497932254538",
              "text": "Please provide the URL to Documented (1) compliance manager job description (2) audit manager job description and (3) risk management job description details.",
              "enableWhen": [
                {
                  "question": "511150511982",
                  "operator": "=",
                  "answerCoding": {
                    "display": "Yes"
                  }
                }
              ],
              "item": [
                {
                  "linkId": "659054713741",
                  "type": "display",
                  "text": "Provide evidence as a URL along with details of Dropbox, Box, Google Drive, Portal, or other storage platforms.",
                  "extension": [
                    {
                      "url": "http://hl7.org/fhir/StructureDefinition/questionnaire-itemControl",
                      "valueCodeableConcept": {
                        "coding": [
                          {
                            "system": "http://hl7.org/fhir/questionnaire-item-control",
                            "code": "help",
                            "display": "Help-Button"
                          }
                        ],
                        "text": "Help-Button"
                      }
                    }
                  ]
                }
              ]
            },
            {
              "type": "display",
              "linkId": "879384515419",
              "_text": {
                "extension": [
                  {
                    "url": "http://hl7.org/fhir/StructureDefinition/rendering-xhtml",
                    "valueString": "<p>If you don't have Documented (1) compliance manager job description (2) audit manager job description and (3) risk management job description details as evidence, you can refer the our sample version <span style=\"color:blue; text-decoration:none; cursor:pointer;\"  onclick=\"window.open('https://suite.opsfolio.com/policies/common/information-technology-quality-infrastructure/general-role', '_blank')\">here</span></p>"
                  }
                ]
              },
              "enableWhen": [
                {
                  "question": "511150511982",
                  "operator": "=",
                  "answerCoding": {
                    "display": "No"
                  }
                }
              ]
            },
            {
              "linkId": "222775951498",
              "type": "display",
              "text": "As evidence, you can provide Documented (1) compliance manager job description (2) audit manager job description and (3) risk management job description details.",
              "extension": [
                {
                  "url": "http://hl7.org/fhir/StructureDefinition/questionnaire-itemControl",
                  "valueCodeableConcept": {
                    "coding": [
                      {
                        "system": "http://hl7.org/fhir/questionnaire-item-control",
                        "code": "help",
                        "display": "Help-Button"
                      }
                    ],
                    "text": "Help-Button"
                  }
                }
              ]
            }
          ],
          "type": "choice",
          "extension": [
            {
              "url": "http://hl7.org/fhir/StructureDefinition/questionnaire-itemControl",
              "valueCodeableConcept": {
                "coding": [
                  {
                    "system": "http://hl7.org/fhir/questionnaire-item-control",
                    "code": "radio-button",
                    "display": "Radio Button"
                  }
                ]
              }
            }
          ],
          "linkId": "511150511982",
          "code": [
            {
              "code": "FII-SCF-HRS-0003"
            }
          ],
          "text": "Are there documented position descriptions for Risk Manager or Audit Manager?",
          "answerOption": [
            {
              "valueCoding": {
                "display": "Yes"
              }
            },
            {
              "valueCoding": {
                "display": "No"
              }
            }
          ]
        },
        {
          "item": [
            {
              "type": "string",
              "linkId": "955976295603",
              "text": "Please provide the URL to Organizational business plans, records of budgets kept, etc.",
              "enableWhen": [
                {
                  "question": "622544475164",
                  "operator": "=",
                  "answerCoding": {
                    "display": "Yes"
                  }
                }
              ],
              "item": [
                {
                  "linkId": "636270141315",
                  "type": "display",
                  "text": "As evidence, you may include a URL along with details from Dropbox, Box, Google Drive, Portal, JIRA, Confluence, GitHub, or any other storage platform that holds documentation such as organizational business plans (meeting minutes) and records of budgets kept.",
                  "extension": [
                    {
                      "url": "http://hl7.org/fhir/StructureDefinition/questionnaire-itemControl",
                      "valueCodeableConcept": {
                        "coding": [
                          {
                            "system": "http://hl7.org/fhir/questionnaire-item-control",
                            "code": "help",
                            "display": "Help-Button"
                          }
                        ],
                        "text": "Help-Button"
                      }
                    }
                  ]
                }
              ]
            },
            {
              "type": "display",
              "linkId": "108912595610",
              "_text": {
                "extension": [
                  {
                    "url": "http://hl7.org/fhir/StructureDefinition/rendering-xhtml",
                    "valueString": "<p>If you don't have Organizational business plans, records of budgets kept, etc. as evidence, you can refer the our sample version <span style=\"color:blue; text-decoration:none; cursor:pointer;\"  onclick=\"window.open('https://suite.opsfolio.com/assets/management-review-meeting.docx', '_blank')\">here</span></p>"
                  }
                ]
              },
              "enableWhen": [
                {
                  "question": "622544475164",
                  "operator": "=",
                  "answerCoding": {
                    "display": "No"
                  }
                }
              ]
            },
            {
              "linkId": "766528483769",
              "type": "display",
              "text": "As evidence, you may include a URL along with details from Dropbox, Box, Google Drive, Portal, JIRA, Confluence, GitHub, or any other storage platform that holds documentation such as organizational business plans (meeting minutes) and records of budgets kept.",
              "extension": [
                {
                  "url": "http://hl7.org/fhir/StructureDefinition/questionnaire-itemControl",
                  "valueCodeableConcept": {
                    "coding": [
                      {
                        "system": "http://hl7.org/fhir/questionnaire-item-control",
                        "code": "help",
                        "display": "Help-Button"
                      }
                    ],
                    "text": "Help-Button"
                  }
                }
              ]
            }
          ],
          "type": "choice",
          "extension": [
            {
              "url": "http://hl7.org/fhir/StructureDefinition/questionnaire-itemControl",
              "valueCodeableConcept": {
                "coding": [
                  {
                    "system": "http://hl7.org/fhir/questionnaire-item-control",
                    "code": "radio-button",
                    "display": "Radio Button"
                  }
                ]
              }
            }
          ],
          "linkId": "622544475164",
          "code": [
            {
              "code": "FII-SCF-BCD-0006"
            }
          ],
          "text": "Does entity maintain organizational business plans and budgets?",
          "answerOption": [
            {
              "valueCoding": {
                "display": "Yes"
              }
            },
            {
              "valueCoding": {
                "display": "No"
              }
            }
          ]
        },
        {
          "type": "string",
          "linkId": "915675977204",
          "code": [
            {
              "code": "FII-SCF-CPL-0001"
            }
          ],
          "text": "Is entity's control framework based on a recognized (NIST 800-53; COBIT; ISO; COSA) framework?",
          "item": [
            {
              "linkId": "977332566339",
              "type": "display",
              "text": "As evidence, you can provide report; certification; policies/procedures/ PowerPoint deck.",
              "extension": [
                {
                  "url": "http://hl7.org/fhir/StructureDefinition/questionnaire-itemControl",
                  "valueCodeableConcept": {
                    "coding": [
                      {
                        "system": "http://hl7.org/fhir/questionnaire-item-control",
                        "code": "help",
                        "display": "Help-Button"
                      }
                    ],
                    "text": "Help-Button"
                  }
                }
              ]
            }
          ]
        },
        {
          "item": [
            {
              "type": "string",
              "linkId": "880000230565",
              "text": "Please provide the URL to Up-to-date registry of regulatory, statutory, legislative and contractual requirements.",
              "enableWhen": [
                {
                  "question": "129953107026",
                  "operator": "=",
                  "answerCoding": {
                    "display": "Yes"
                  }
                }
              ],
              "item": [
                {
                  "linkId": "630913261567",
                  "type": "display",
                  "text": "Provide evidence as a URL along with details of Dropbox, Box, Google Drive, Portal, or other storage platforms.",
                  "extension": [
                    {
                      "url": "http://hl7.org/fhir/StructureDefinition/questionnaire-itemControl",
                      "valueCodeableConcept": {
                        "coding": [
                          {
                            "system": "http://hl7.org/fhir/questionnaire-item-control",
                            "code": "help",
                            "display": "Help-Button"
                          }
                        ],
                        "text": "Help-Button"
                      }
                    }
                  ]
                }
              ]
            },
            {
              "type": "display",
              "linkId": "816423446395",
              "_text": {
                "extension": [
                  {
                    "url": "http://hl7.org/fhir/StructureDefinition/rendering-xhtml",
                    "valueString": "<p>If you don't have Up-to-date registry of regulatory, statutory, legislative and contractual requirements as evidence, you can refer the our sample version <span style=\"color:blue; text-decoration:none; cursor:pointer;\"  onclick=\"window.open('https://suite.opsfolio.com/policies/common/information-technology-quality-infrastructure/compliance-regulatory-policy', '_blank')\">here</span></p>"
                  }
                ]
              },
              "enableWhen": [
                {
                  "question": "129953107026",
                  "operator": "=",
                  "answerCoding": {
                    "display": "No"
                  }
                }
              ]
            },
            {
              "linkId": "345172735619",
              "type": "display",
              "text": "As evidence, you can provide Up-to-date registry of regulatory, statutory, legislative and contractual requirements.",
              "extension": [
                {
                  "url": "http://hl7.org/fhir/StructureDefinition/questionnaire-itemControl",
                  "valueCodeableConcept": {
                    "coding": [
                      {
                        "system": "http://hl7.org/fhir/questionnaire-item-control",
                        "code": "help",
                        "display": "Help-Button"
                      }
                    ],
                    "text": "Help-Button"
                  }
                }
              ]
            }
          ],
          "type": "choice",
          "extension": [
            {
              "url": "http://hl7.org/fhir/StructureDefinition/questionnaire-itemControl",
              "valueCodeableConcept": {
                "coding": [
                  {
                    "system": "http://hl7.org/fhir/questionnaire-item-control",
                    "code": "radio-button",
                    "display": "Radio Button"
                  }
                ]
              }
            }
          ],
          "linkId": "129953107026",
          "code": [
            {
              "code": "FII-SCF-GOV-0006"
            }
          ],
          "text": "Policies and procedures related to the relevant statutory, regulatory, legislative and contractual requirements",
          "answerOption": [
            {
              "valueCoding": {
                "display": "Yes"
              }
            },
            {
              "valueCoding": {
                "display": "No"
              }
            }
          ]
        },
        {
          "item": [
            {
              "type": "string",
              "linkId": "350361450291",
              "text": "Please provide the URL to Master list of system components (servers, Operating systems, databases, etc.)",
              "enableWhen": [
                {
                  "question": "852930816404",
                  "operator": "=",
                  "answerCoding": {
                    "display": "Yes"
                  }
                }
              ],
              "item": [
                {
                  "linkId": "180494544271",
                  "type": "display",
                  "text": "Provide evidence as a URL along with details of Dropbox, Box, Google Drive, Portal, or other storage platforms.",
                  "extension": [
                    {
                      "url": "http://hl7.org/fhir/StructureDefinition/questionnaire-itemControl",
                      "valueCodeableConcept": {
                        "coding": [
                          {
                            "system": "http://hl7.org/fhir/questionnaire-item-control",
                            "code": "help",
                            "display": "Help-Button"
                          }
                        ],
                        "text": "Help-Button"
                      }
                    }
                  ]
                }
              ]
            },
            {
              "type": "display",
              "linkId": "896154705473",
              "_text": {
                "extension": [
                  {
                    "url": "http://hl7.org/fhir/StructureDefinition/rendering-xhtml",
                    "valueString": "<p>If you don't have Master list of system components (servers, Operating systems, databases, etc.) as evidence, you can refer the our sample version <span style=\"color:blue; text-decoration:none; cursor:pointer;\"  onclick=\"window.open('https://suite.opsfolio.com/assets/asset-list.xlsx', '_blank')\">here</span></p>"
                  }
                ]
              },
              "enableWhen": [
                {
                  "question": "852930816404",
                  "operator": "=",
                  "answerCoding": {
                    "display": "No"
                  }
                }
              ]
            },
            {
              "linkId": "722608167626",
              "type": "display",
              "text": "As evidence, you can provide Master list of system components (servers, Operating systems, databases, etc.)",
              "extension": [
                {
                  "url": "http://hl7.org/fhir/StructureDefinition/questionnaire-itemControl",
                  "valueCodeableConcept": {
                    "coding": [
                      {
                        "system": "http://hl7.org/fhir/questionnaire-item-control",
                        "code": "help",
                        "display": "Help-Button"
                      }
                    ],
                    "text": "Help-Button"
                  }
                }
              ]
            }
          ],
          "type": "choice",
          "extension": [
            {
              "url": "http://hl7.org/fhir/StructureDefinition/questionnaire-itemControl",
              "valueCodeableConcept": {
                "coding": [
                  {
                    "system": "http://hl7.org/fhir/questionnaire-item-control",
                    "code": "radio-button",
                    "display": "Radio Button"
                  }
                ]
              }
            }
          ],
          "linkId": "852930816404",
          "code": [
            {
              "code": "FII-SCF-HRS-0009.1"
            }
          ],
          "text": "Does management maintain an asset inventory?",
          "answerOption": [
            {
              "valueCoding": {
                "display": "Yes"
              }
            },
            {
              "valueCoding": {
                "display": "No"
              }
            }
          ]
        },
        {
          "item": [
            {
              "type": "string",
              "linkId": "770288783839",
              "text": "Please provide the URL to Most recently completed risk assessment details.",
              "enableWhen": [
                {
                  "question": "483977777111",
                  "operator": "=",
                  "answerCoding": {
                    "display": "Yes"
                  }
                }
              ],
              "item": [
                {
                  "linkId": "847825518266",
                  "type": "display",
                  "text": "Provide evidence as a URL along with details of Dropbox, Box, Google Drive, Portal, or other storage platforms.",
                  "extension": [
                    {
                      "url": "http://hl7.org/fhir/StructureDefinition/questionnaire-itemControl",
                      "valueCodeableConcept": {
                        "coding": [
                          {
                            "system": "http://hl7.org/fhir/questionnaire-item-control",
                            "code": "help",
                            "display": "Help-Button"
                          }
                        ],
                        "text": "Help-Button"
                      }
                    }
                  ]
                }
              ]
            },
            {
              "type": "display",
              "linkId": "351189429724",
              "_text": {
                "extension": [
                  {
                    "url": "http://hl7.org/fhir/StructureDefinition/rendering-xhtml",
                    "valueString": "<p>If you don't have Most recently completed risk assessment details as evidence, you can refer the our sample version <span style=\"color:blue; text-decoration:none; cursor:pointer;\"  onclick=\"window.open('https://suite.opsfolio.com/assets/risk-rgister.xlsx', '_blank')\">here</span></p>"
                  }
                ]
              },
              "enableWhen": [
                {
                  "question": "483977777111",
                  "operator": "=",
                  "answerCoding": {
                    "display": "No"
                  }
                }
              ]
            },
            {
              "linkId": "723211870273",
              "type": "display",
              "text": "As evidence, you can provide Most recently completed risk assessment details.",
              "extension": [
                {
                  "url": "http://hl7.org/fhir/StructureDefinition/questionnaire-itemControl",
                  "valueCodeableConcept": {
                    "coding": [
                      {
                        "system": "http://hl7.org/fhir/questionnaire-item-control",
                        "code": "help",
                        "display": "Help-Button"
                      }
                    ],
                    "text": "Help-Button"
                  }
                }
              ]
            }
          ],
          "type": "choice",
          "extension": [
            {
              "url": "http://hl7.org/fhir/StructureDefinition/questionnaire-itemControl",
              "valueCodeableConcept": {
                "coding": [
                  {
                    "system": "http://hl7.org/fhir/questionnaire-item-control",
                    "code": "radio-button",
                    "display": "Radio Button"
                  }
                ]
              }
            }
          ],
          "linkId": "483977777111",
          "code": [
            {
              "code": "FII-SCF-RSK-0003"
            }
          ],
          "text": "Can management provide the most recently completed risk assessment?",
          "answerOption": [
            {
              "valueCoding": {
                "display": "Yes"
              }
            },
            {
              "valueCoding": {
                "display": "No"
              }
            }
          ]
        },
        {
          "item": [
            {
              "type": "string",
              "linkId": "835534492455",
              "text": "Please provide the URL to Most recently completed fraud assessment details.",
              "enableWhen": [
                {
                  "question": "782945372513",
                  "operator": "=",
                  "answerCoding": {
                    "display": "Yes"
                  }
                }
              ],
              "item": [
                {
                  "linkId": "623631307653",
                  "type": "display",
                  "text": "Provide evidence as a URL along with details of Dropbox, Box, Google Drive, Portal, or other storage platforms.",
                  "extension": [
                    {
                      "url": "http://hl7.org/fhir/StructureDefinition/questionnaire-itemControl",
                      "valueCodeableConcept": {
                        "coding": [
                          {
                            "system": "http://hl7.org/fhir/questionnaire-item-control",
                            "code": "help",
                            "display": "Help-Button"
                          }
                        ],
                        "text": "Help-Button"
                      }
                    }
                  ]
                }
              ]
            },
            {
              "type": "display",
              "linkId": "846103061828",
              "_text": {
                "extension": [
                  {
                    "url": "http://hl7.org/fhir/StructureDefinition/rendering-xhtml",
                    "valueString": "<p>If you don't have Most recently completed fraud assessment details as evidence, you can refer the our sample version <span style=\"color:blue; text-decoration:none; cursor:pointer;\"  onclick=\"window.open('https://suite.opsfolio.com/assets/fraud-assessment-review.xlsx', '_blank')\">here</span></p>"
                  }
                ]
              },
              "enableWhen": [
                {
                  "question": "782945372513",
                  "operator": "=",
                  "answerCoding": {
                    "display": "No"
                  }
                }
              ]
            },
            {
              "linkId": "878288739022",
              "type": "display",
              "text": "As evidence, you can provide Most recently completed fraud assessment details.",
              "extension": [
                {
                  "url": "http://hl7.org/fhir/StructureDefinition/questionnaire-itemControl",
                  "valueCodeableConcept": {
                    "coding": [
                      {
                        "system": "http://hl7.org/fhir/questionnaire-item-control",
                        "code": "help",
                        "display": "Help-Button"
                      }
                    ],
                    "text": "Help-Button"
                  }
                }
              ]
            }
          ],
          "type": "choice",
          "extension": [
            {
              "url": "http://hl7.org/fhir/StructureDefinition/questionnaire-itemControl",
              "valueCodeableConcept": {
                "coding": [
                  {
                    "system": "http://hl7.org/fhir/questionnaire-item-control",
                    "code": "radio-button",
                    "display": "Radio Button"
                  }
                ]
              }
            }
          ],
          "linkId": "782945372513",
          "code": [
            {
              "code": "FII-SCF-RSK-0004.1"
            }
          ],
          "text": "Can management provide the most recently completed risk assessment that includes fraud risk factors? including evidence that the assessment:- identifies and assesses the types of fraud that could impact business and operations (e.g. fraudulent reporting, loss of assets, unauthorized system access, overriding con",
          "answerOption": [
            {
              "valueCoding": {
                "display": "Yes"
              }
            },
            {
              "valueCoding": {
                "display": "No"
              }
            }
          ]
        },
        {
          "type": "string",
          "linkId": "154887827645",
          "code": [
            {
              "code": "FII-SCF-VPM-0006"
            }
          ],
          "text": "Are vulnerability scans or penetration testing performed on a periodic basis?",
          "item": [
            {
              "linkId": "903261752170",
              "type": "display",
              "text": "As evidence, you may include a URL along with details from Dropbox, Box, Google Drive, Portal, JIRA, Confluence, GitHub, or any other storage platform that holds the most recent network internal and external vulnerability scan/penetration test reports.",
              "extension": [
                {
                  "url": "http://hl7.org/fhir/StructureDefinition/questionnaire-itemControl",
                  "valueCodeableConcept": {
                    "coding": [
                      {
                        "system": "http://hl7.org/fhir/questionnaire-item-control",
                        "code": "help",
                        "display": "Help-Button"
                      }
                    ],
                    "text": "Help-Button"
                  }
                }
              ]
            }
          ]
        },
        {
          "item": [
            {
              "type": "string",
              "linkId": "330220718247",
              "text": "Please provide the URL to Business Continuity/Disaster Recovery Plan details.",
              "enableWhen": [
                {
                  "question": "572830451814",
                  "operator": "=",
                  "answerCoding": {
                    "display": "Yes"
                  }
                }
              ],
              "item": [
                {
                  "linkId": "526646085881",
                  "type": "display",
                  "text": "Provide evidence as a URL along with details of Dropbox, Box, Google Drive, Portal, or other storage platforms.",
                  "extension": [
                    {
                      "url": "http://hl7.org/fhir/StructureDefinition/questionnaire-itemControl",
                      "valueCodeableConcept": {
                        "coding": [
                          {
                            "system": "http://hl7.org/fhir/questionnaire-item-control",
                            "code": "help",
                            "display": "Help-Button"
                          }
                        ],
                        "text": "Help-Button"
                      }
                    }
                  ]
                }
              ]
            },
            {
              "type": "display",
              "linkId": "699960007077",
              "_text": {
                "extension": [
                  {
                    "url": "http://hl7.org/fhir/StructureDefinition/rendering-xhtml",
                    "valueString": "<p>If you don't have Business Continuity/Disaster Recover Plan details as evidence, you can refer the our sample version <span style=\"color:blue; text-decoration:none; cursor:pointer;\"  onclick=\"window.open('https://suite.opsfolio.com/policies/common/information-technology-quality-infrastructure/business-continuity-plan', '_blank')\">here</span></p>"
                  }
                ]
              },
              "enableWhen": [
                {
                  "question": "572830451814",
                  "operator": "=",
                  "answerCoding": {
                    "display": "No"
                  }
                }
              ]
            },
            {
              "linkId": "922358583482",
              "type": "display",
              "text": "As evidence, you can provide Business Continuity/Disaster Recovery Plan details.",
              "extension": [
                {
                  "url": "http://hl7.org/fhir/StructureDefinition/questionnaire-itemControl",
                  "valueCodeableConcept": {
                    "coding": [
                      {
                        "system": "http://hl7.org/fhir/questionnaire-item-control",
                        "code": "help",
                        "display": "Help-Button"
                      }
                    ],
                    "text": "Help-Button"
                  }
                }
              ]
            }
          ],
          "type": "choice",
          "extension": [
            {
              "url": "http://hl7.org/fhir/StructureDefinition/questionnaire-itemControl",
              "valueCodeableConcept": {
                "coding": [
                  {
                    "system": "http://hl7.org/fhir/questionnaire-item-control",
                    "code": "radio-button",
                    "display": "Radio Button"
                  }
                ]
              }
            }
          ],
          "linkId": "572830451814",
          "code": [
            {
              "code": "FII-SCF-BCD-0001"
            }
          ],
          "text": "Is a comprehensive disaster recovery and business continuity plan in place and communicated to relevant personnel?",
          "answerOption": [
            {
              "valueCoding": {
                "display": "Yes"
              }
            },
            {
              "valueCoding": {
                "display": "No"
              }
            }
          ]
        },
        {
          "type": "string",
          "linkId": "757635013794",
          "code": [
            {
              "code": "FII-SCF-BCD-0002.3"
            }
          ],
          "text": "Is the disaster recovery program tested on a periodic basis to ensure adequate recovery?",
          "item": [
            {
              "linkId": "663733395217",
              "type": "display",
              "text": "As evidence, you may include a URL along with details from Dropbox, Box, Google Drive, Portal, JIRA, Confluence, GitHub, or any other storage platform that holds documentation for the most recently completed disaster recovery tests details.",
              "extension": [
                {
                  "url": "http://hl7.org/fhir/StructureDefinition/questionnaire-itemControl",
                  "valueCodeableConcept": {
                    "coding": [
                      {
                        "system": "http://hl7.org/fhir/questionnaire-item-control",
                        "code": "help",
                        "display": "Help-Button"
                      }
                    ],
                    "text": "Help-Button"
                  }
                }
              ]
            }
          ]
        }
      ],
      "type": "group",
      "extension": [
        {
          "url": "http://hl7.org/fhir/StructureDefinition/questionnaire-itemControl",
          "valueCodeableConcept": {
            "coding": [
              {
                "system": "http://hl7.org/fhir/questionnaire-item-control",
                "code": "radio-button",
                "display": "Radio Button"
              }
            ]
          }
        }
      ],
      "linkId": "177288750351",
      "text": "Common Criteria Related to Risk Assessment"
    },
    {
      "type": "group",
      "linkId": "282577431639",
      "text": "Meta Information",
      "_text": {
        "extension": [
          {
            "url": "http://hl7.org/fhir/StructureDefinition/rendering-xhtml",
            "valueString": "<div style=\"display:none\">\n<input  id=\"lhcFormMetaInformation\" value='{\n    \"createdAt\": \"2-10-2025\",\n    \"createdBy\": \"Arun KR\",\n    \"description\": \"As part of Plan 2, this option provides a balanced compliance approach by allowing organizations to retain their own IT and HR policies while leveraging our technical policies to meet SOC 2 requirements. Designed for organizations seeking a structured yet flexible compliance framework, it ensures alignment with SOC 2 standards while maintaining existing operational policies. This approach helps streamline audit preparation by integrating proven technical controls with an organization’s established policies. The following questionnaire is intended to collect Risk Assessment informations and assess readiness for SOC 2 compliance.\",\n    \"title\": \"Risk Assessment\",\n    \"organization\": \"Netspective Communication LLC\"\n}'>\n</div>"
          }
        ]
      }
    }
  ]
}